shiny_invoice/__init__.py
shiny_invoice/config.py
shiny_invoice/shiny_invoice.py
shiny_invoice/ui_config.py
shiny_invoice/ui_existing_invoices.py
shiny_invoice/ui_new_invoice.py
shiny_invoice/templates/default_de.html
shiny_invoice/templates/default_en.html
shiny_invoice-0.4.0.dist-info/LICENSE
shiny_invoice-0.4.0.dist-info/METADATA
shiny_invoice-0.4.0.dist-info/WHEEL
shiny_invoice-0.4.0.dist-info/entry_points.txt
shiny_invoice-0.4.0.dist-info/top_level.txt
shiny_invoice-0.4.0.dist-info/RECORD
