Metadata-Version: 2.1
Name: shiny-invoice
Version: 0.4.0
Summary: Simply manage invoices
License: MIT License
Keywords: invoice,finance,accounting
Classifier: Development Status :: 3 - Alpha
Classifier: License :: OSI Approved :: MIT License
Classifier: Programming Language :: Python
Classifier: Programming Language :: Python :: 3
Classifier: Programming Language :: Python :: 3.12
Classifier: Topic :: Office/Business :: Financial :: Accounting
Requires-Python: >=3.12
License-File: LICENSE
Requires-Dist: shiny
Requires-Dist: click
Requires-Dist: ruamel.yaml
Requires-Dist: pandas
Requires-Dist: pydantic
Requires-Dist: tinydb
Provides-Extra: dev
Requires-Dist: black; extra == "dev"
Requires-Dist: pylint; extra == "dev"
Requires-Dist: pre-commit; extra == "dev"
